{
  "type": "minecraft:chest",
  "pools": [
    {
      "bonus_rolls": 0.0,
      "entries": [
        {
          "type": "minecraft:item",
          "functions": [
            {
              "add": false,
              "count": 8.0,
              "function": "minecraft:set_count"
            }
          ],
          "name": "minecraft:sand"
        },
        {
          "type": "minecraft:item",
          "functions": [
            {
              "add": false,
              "count": 6.0,
              "function": "minecraft:set_count"
            }
          ],
          "name": "biomesoplenty:sea_oats"
        },
        {
          "type": "minecraft:item",
          "functions": [
            {
              "add": false,
              "count": 6.0,
              "function": "minecraft:set_count"
            }
          ],
          "name": "biomesoplenty:dune_grass"
        }
      ],
      "rolls": 1.0
    }
  ]
}